teyit.py
teyit-0.4.3.dist-info/LICENSE.txt
teyit-0.4.3.dist-info/METADATA
teyit-0.4.3.dist-info/WHEEL
teyit-0.4.3.dist-info/entry_points.txt
teyit-0.4.3.dist-info/top_level.txt
teyit-0.4.3.dist-info/RECORD
