Metadata-Version: 2.1
Name: teyit
Version: 0.4.3
Summary: Unittest assertion formatter
Home-page: https://github.com/isidentical/teyit
Author: isidentical
Author-email: isidentical@gmail.com
License: MIT
Classifier: License :: OSI Approved :: MIT License
Classifier: Programming Language :: Python :: 3
Classifier: Programming Language :: Python :: 3 :: Only
Classifier: Programming Language :: Python :: 3.9
Classifier: Programming Language :: Python :: 3.10
Requires-Python: >=3.9
License-File: LICENSE.txt
Requires-Dist: refactor (>=0.4.4)
